sanest/__init__.py
sanest/sanest.py
sanest-0.1.0.dist-info/DESCRIPTION.rst
sanest-0.1.0.dist-info/LICENSE.txt
sanest-0.1.0.dist-info/METADATA
sanest-0.1.0.dist-info/RECORD
sanest-0.1.0.dist-info/WHEEL
sanest-0.1.0.dist-info/metadata.json
sanest-0.1.0.dist-info/top_level.txt
