Metadata-Version: 2.0
Name: sanest
Version: 0.1.0
Summary: sane nested dictionaries and lists
Home-page: https://github.com/wbolster/sanest
Author: wouter bolsterlee
Author-email: wouter@bolsterl.ee
License: BSD
Platform: UNKNOWN
Classifier: Development Status :: 5 - Production/Stable
Classifier: Intended Audience :: Developers
Classifier: License :: OSI Approved :: BSD License
Classifier: Programming Language :: Python
Classifier: Programming Language :: Python :: 3
Classifier: Programming Language :: Python :: 3 :: Only
Classifier: Topic :: Software Development :: Libraries
Classifier: Topic :: Software Development :: Libraries :: Python Modules
